Workbook

Sheet Summary
A1: TallyFlow - cost to run, per month
A2: Every figure is a formula. Change the Assumptions sheet and this updates.
A4: Option | B4: Per month (INR) | C4: Per customer | D4: Ceiling | E4: When to pick it
A5: A - Hetzner single box | B5: ='Monthly cost'!C12+'Annual & one-time'!C11 | C5: =B5/Assumptions!$B$8 | D5: ~250 companies | E5: Pilot and first paying customers. Runs your existing compose file unchanged.
A6: B - DigitalOcean Bangalore | B6: ='Monthly cost'!C25+'Annual & one-time'!C11 | C6: =B6/Assumptions!$B$8 | D6: ~500 companies | E6: Production. Managed Postgres with automated backups, India region, no database ops.
A7: C - AWS Mumbai (low) | B7: ='Monthly cost'!B36+'Annual & one-time'!C11 | C7: =B7/Assumptions!$B$8 | D7: elastic | E7: Only if a customer contractually demands AWS or an enterprise audit trail.
A8: C - AWS Mumbai (high) | B8: ='Monthly cost'!C36+'Annual & one-time'!C11 | C8: =B8/Assumptions!$B$8 | D8: elastic
A10: Option B at other scales | B10: Per month (INR) | C10: Per customer | D10: Orgs | E10: Note
A11: Pilot | B11: ='Monthly cost'!B25+'Annual & one-time'!C11 | C11: =B11/D11 | D11: 25 | E11: Where you are today
A12: Growing | B12: ='Monthly cost'!C25+'Annual & one-time'!C11 | C12: =B12/D12 | D12: 100 | E12: Second API container not needed yet
A13: Scaled | B13: ='Monthly cost'!D25+'Annual & one-time'!C11 | C13: =B13/D13 | D13: 500 | E13: Two API containers plus Redis
A16: Recommendation
A17: • Start on Option A. It runs the exact stack already in deploy/uat and costs about as much per month as one lunch.
A18: • Move to Option B before taking money from customers you do not know personally. The managed database's automated backups are the reason, not the CPU.
A19: • Infrastructure is not what this product costs. Support time will dominate long before servers do.
A21: Two findings in the code that change these numbers
A22: audit_logs and job_stats are never pruned.
A23: LogWriter._prune covers server_logs at 30 days and connector_logs at 14 days. Nothing deletes the other two. JobStat's own docstring says it is 'safe to aggressively prune' and no pruner exists. At the assumed scale that is roughly 15 GB a year of telemetry, and it is what pushes you into the next database tier before customer data does. A retention window on both is the highest-leverage cost fix available.
A25: The second API instance is a step change, not a slope.
A26: One uvicorn worker means one container. The moment you need two you also need TALLYFLOW_REDIS_URL and a managed Redis. Budget for it at roughly 250 companies - see the Sizing model sheet.
A28: Prices verified August 2026 from digitalocean.com/pricing/managed-databases, digitalocean.com/pricing/droplets, and Hetzner Cloud list prices following the April 2026 increase. The AWS Mumbai figures are an indicative band, not a line-verified quote.

Sheet Assumptions
A1: Assumptions
A2: Yellow cells are inputs. Change them and every other sheet recalculates.
A4: Input | B4: Value | C4: Basis
A5: USD to INR | B5: 88 | C5: Set to today's rate before quoting this to anyone.
A6: EUR to INR | B6: 95 | C6: Set to today's rate before quoting this to anyone.
A7: GST on cloud services | B7: 0.18 | C7: Applies when billed to an Indian entity.
A8: Customer organisations | B8: 100 | C8: The scale being costed.
A9: Tally companies per org | B9: 1.5 | C9: Most shops run one; some run two or three.
A10: Phone users per org | B10: 3 | C10: Owner plus staff.
A11: Vouchers per day per company | B11: 100 | C11: Medium shop. Small is 30, large is 300.
A12: History retained (years) | B12: 4 | C12: config.py: sync_max_history_years.
A13: Inventory-line window (days) | B13: 400 | C13: config.py: sync_inventory_days.
A14: Snapshot staleness (minutes) | B14: 15 | C14: config.py: snapshot_stale_after_seconds.
A15: Delta sync interval (minutes) | B15: 5 | C15: config.py: sync_delta_interval_seconds.
A16: Releases per year | B16: 6 | C16: Each one pushes 61.6 MB to every existing customer.
A18: Fixed measurements taken from the repository
A19: Measurement | B19: Value | C19: Where it comes from
A20: Android APK size (MB) | B20: 23.6 | C20: deploy/uat/downloads/TallyFlow-0.1.0.apk
A21: Connector installer size (MB) | B21: 38.1 | C21: deploy/uat/downloads/TallyFlowConnector-Setup-0.1.0.exe
A22: Warm datasets refreshed | B22: 4 | C22: refresher.py WARM_DATASETS, less vouchers.list which the sync owns
A23: Voucher JSON with inventory (KB) | B23: 2.5 | C23: Voucher plus ledger and inventory entries. Estimated.
A24: Voucher JSON without lines (KB) | B24: 0.9 | C24: Slices older than the inventory window omit line items.
A25: Index and row overhead | B25: 0.35 | C25: Postgres JSON plus four indexes on voucher_records.
A26: App egress per org (GB/month) | B26: 0.5 | C26: Backend to phones. Snapshot DTOs are small.
A27: Audited requests per user per day | B27: 150 | C27: One audit_logs row per request.

Sheet Sizing model
A1: Sizing model
A2: Derived from the assumptions. This is what decides the server and database tier.
A4: Per company | B4: Small 30/day | C4: Medium 100/day | D4: Large 300/day | E4: Note
A5: Vouchers per day | B5: 30 | C5: 100 | D5: 300 | E5: Posted transactions of all types
A6: Vouchers stored | B6: =B5*365*Assumptions!$B$12 | C6: =C5*365*Assumptions!$B$12 | D6: =D5*365*Assumptions!$B$12 | E6: voucher_records keeps one row per voucher
A7: of which carry inventory lines | B7: =B5*Assumptions!$B$13 | C7: =C5*Assumptions!$B$13 | D7: =D5*Assumptions!$B$13 | E7: Older slices omit line items by design
A8: Voucher storage | B8: =((B7*Assumptions!$B$23)+((B6-B7)*Assumptions!$B$24))/1024*(1+Assumptions!$B$25) | C8: =((C7*Assumptions!$B$23)+((C6-C7)*Assumptions!$B$24))/1024*(1+Assumptions!$B$25) | D8: =((D7*Assumptions!$B$23)+((D6-D7)*Assumptions!$B$24))/1024*(1+Assumptions!$B$25) | E8: Includes index and row overhead
A9: Snapshots (five datasets) | B9: 3 | C9: 5 | D9: 12 | E9: Stock items and outstanding bills dominate
A10: job_stats, one year, unpruned | B10: =(Assumptions!$B$22*60/Assumptions!$B$14+60/Assumptions!$B$15)*24*365*0.2/1024 | C10: =(Assumptions!$B$22*60/Assumptions!$B$14+60/Assumptions!$B$15)*24*365*0.2/1024 | D10: =(Assumptions!$B$22*60/Assumptions!$B$14+60/Assumptions!$B$15)*24*365*0.2/1024 | E10: One row per connector job. NOTHING DELETES THIS.
A11: Total per company | B11: =SUM(B8:B10) | C11: =SUM(C8:C10) | D11: =SUM(D8:D10) | E11: The planning figure
A13: At the assumed scale
A14: Fleet total | B14: Value | E14: Note
A15: Companies under management | B15: =Assumptions!$B$8*Assumptions!$B$9 | E15: organisations x companies per org
A16: Connector round-trips per hour | B16: =B15*(Assumptions!$B$22*60/Assumptions!$B$14+60/Assumptions!$B$15) | E16: Warm refresh plus delta sync
A17: Connector round-trips per second | B17: =B16/3600 | E17: Trivial as request count. Parsing the responses is the real limit.
A18: Database size (medium blend) | B18: =B15*C11/1024 | E18: Choose the database tier from this
A19: audit_logs growth per year | B19: =Assumptions!$B$8*Assumptions!$B$10*Assumptions!$B$27*365*0.4/1024/1024 | E19: One row per request. NOTHING DELETES THIS EITHER.
A20: App egress per month | B20: =Assumptions!$B$8*Assumptions!$B$26 | E20: Backend to phones
A21: Download egress per month | B21: =(Assumptions!$B$8*(Assumptions!$B$20+Assumptions!$B$21)*Assumptions!$B$16/12)/1024 | E21: Updates pushed to the existing fleet
A22: Total egress per month | B22: =SUM(B20:B21) | E22: Inbound from connectors is free on every option costed here
A24: Scaling limit
A25: • The backend runs ONE uvicorn worker. Connectors hold long-lived WebSockets to a specific process, so forks would each hold a different set of sockets with no way to route between them.
A26: • The ceiling is not request count, it is response parsing. stock_items.list revalidated four times an hour per company is roughly 2,800 pydantic model validations per second at 500 companies, which saturates a single Python process.
A27: • Practical ceiling for one instance: 150 to 300 active companies. Beyond that you add containers and a Redis, which is a step change in cost rather than a slope.

Sheet Monthly cost
A1: Monthly cost by option
A2: Provider list prices verified August 2026. Shaded rows are totals.
A4: Option A - Hetzner single box (runs deploy/uat/docker-compose.yml unchanged)
A5: Line item | B5: EUR | C5: INR | F5: Note
A6: CX33 - 4 vCPU / 8 GB / 80 GB NVMe / 20 TB | B6: 8.49 | C6: =B6*Assumptions!$B$6 | F6: Germany or Finland. Not Singapore - see note below.
A7: IPv4 address | B7: 0.5 | C7: =B7*Assumptions!$B$6
A8: Server backups (20% of server) | B8: =B6*0.2 | C8: =B8*Assumptions!$B$6 | F8: Hetzner automated snapshots
A9: Off-site database dumps (Backblaze B2) | B9: 0.1 | C9: =B9*Assumptions!$B$6 | F9: Never keep the only backup on the same host
A10: Block storage beyond the included 80 GB | B10: =MAX(0,'Sizing model'!B18-80)*0.05 | C10: =B10*Assumptions!$B$6 | F10: About EUR 0.05/GB/month. Starts to bite around 250 companies.
A11: Domain (.in, amortised) | B11: 1 | C11: =B11*Assumptions!$B$6 | F11: TLS is free - Caddy plus Let's Encrypt is already wired
A12: Total | B12: =SUM(B6:B11) | C12: =SUM(C6:C11) | F12: No GST - billed from Germany
A15: Option B - DigitalOcean Bangalore with managed Postgres (recommended for production)
A16: Line item | B16: Pilot ~25 orgs | C16: ~100 orgs | D16: ~500 orgs | F16: Note
A17: Droplet - API, Caddy, website, portal | B17: 24 | C17: 48 | D17: 96 | F17: 2 vCPU/4 GB, then 4 vCPU/8 GB, then two of them
A18: Managed PostgreSQL | B18: 30.45 | C18: 60.9 | D18: 122.1 | F18: 2 GiB, then 4 GiB, then 8 GiB. Storage I/O is included, no IOPS fees.
A19: Managed Redis / Valkey | B19: 0 | C19: 0 | D19: 15 | F19: Only needed once there is a second API container
A20: Spaces - downloads and CDN | B20: 5 | C20: 5 | D20: 5 | F20: 250 GB storage and 1 TB transfer included
A21: Droplet backups (20%) | B21: =B17*0.2 | C21: =C17*0.2 | D21: =D17*0.2
A22: Subtotal (USD) | B22: =SUM(B17:B21) | C22: =SUM(C17:C21) | D22: =SUM(D17:D21)
A23: GST | B23: =B22*Assumptions!$B$7 | C23: =C22*Assumptions!$B$7 | D23: =D22*Assumptions!$B$7 | F23: If billed to an Indian entity
A24: Total (USD incl. GST) | B24: =B22+B23 | C24: =C22+C23 | D24: =D22+D23
A25: Total (INR incl. GST) | B25: =B24*Assumptions!$B$5 | C25: =C24*Assumptions!$B$5 | D25: =D24*Assumptions!$B$5
A28: Option C - AWS Mumbai (indicative band, not a line-verified quote)
A29: Line item | B29: Low USD | C29: High USD | F29: Note
A30: EC2 t4g.medium | B30: 16 | C30: 25 | F30: ap-south-1 on-demand
A31: RDS PostgreSQL db.t4g.medium, Multi-AZ | B31: 95 | C31: 120 | F31: Mumbai carries a premium over us-east-1
A32: Application Load Balancer | B32: 20 | C32: 25 | F32: Needed to terminate TLS and WebSockets
A33: EBS, snapshots, CloudWatch | B33: 25 | C33: 45
A34: Egress (metered) | B34: ='Sizing model'!B22*0.109 | C34: ='Sizing model'!B22*0.109 | F34: About $0.109/GB. The only option here that meters this.
A35: Subtotal (USD) | B35: =SUM(B30:B34) | C35: =SUM(C30:C34)
A36: Total (INR incl. GST) | B36: =B35*(1+Assumptions!$B$7)*Assumptions!$B$5 | C36: =C35*(1+Assumptions!$B$7)*Assumptions!$B$5 | F36: Roughly three times Option B for the same capacity
A39: Regional warning
A40: • On Hetzner, pick Germany or Finland. The Singapore region includes only 0.5 TB of traffic and charges EUR 7.40 per extra TB, against 20 TB included and EUR 1 per TB in the EU. Germany to India adds about 130 ms, which does not matter here because the phone reads stored snapshots rather than live Tally.

Sheet Annual & one-time
A1: Costs outside the server bill
A2: The monthly column is amortised into the Summary sheet.
A4: Item | B4: Per year (INR) | C4: Per month (INR) | D4: Note
A5: Domain (.in) | B5: 1000 | C5: =B5/12 | D5: Renew annually. TLS is free through Caddy and Let's Encrypt.
A6: Code-signing certificate (OV) | B6: 30000 | C6: =B6/12 | D6: Recommended. Without it SmartScreen warns every customer who downloads the connector. OV certificates now require a hardware token or HSM, which is why this is not an 80-dollar line any more.
A7: Google Play / App Store | B7: 0 | C7: =B7/12 | D7: Not applicable - you distribute the APK yourself. That decision is also why download bandwidth sits on your own bill.
A8: Monitoring / APM | B8: 0 | C8: =B8/12 | D8: The portal's own log surfaces already answer 'why did it stop working for this customer' - server_logs, connector log_batch and the SSE tail.
A9: Transactional email | B9: 0 | C9: =B9/12 | D9: No SMTP or email provider is wired in. Verified by grep across apps/backend.
A10: Object storage / CDN | B10: 0 | C10: =B10/12 | D10: Already inside the option above - Spaces on DigitalOcean, or Caddy serving /downloads on Hetzner.
A11: Total | B11: =SUM(B5:B10) | C11: =SUM(C5:C10)
A14: One-time, non-recurring
A15: Item | B15: INR | D15: Note
A16: Initial backfill bandwidth | B16: 0 | D16: 50 to 150 MB per company, inbound. Free on every provider costed here.
A17: Migration and setup labour | B17: 0 | D17: run.py handles it and DEPLOYMENT.md is the runbook. Cost is your time, not cash.
